LICENSE
MANIFEST.in
PKG-INFO
README
TODO
setup.py
bcrypt/__init__.py
bcrypt/bcrypt.c
bcrypt/bcrypt_python.c
bcrypt/blowfish.c
bcrypt/pybc_blf.h
py_bcrypt_w32.egg-info/PKG-INFO
py_bcrypt_w32.egg-info/SOURCES.txt
py_bcrypt_w32.egg-info/dependency_links.txt
py_bcrypt_w32.egg-info/top_level.txt
test/test.py