Metadata-Version: 1.0
Name: py-bcrypt-w32
Version: 0.2.2
Summary: Blowfish password hashing
Home-page: http://code.google.com/r/djpnewton-py-bcrypt/
Author: Daniel Newton
Author-email: djpnewton@gmail.com
License: BSD
Platform: UNKNOWN
